{"cameraMode":{"drawMode":0,"name":"Shaded","section":"Shading Mode"},"sceneLighting":true,"audioPlay":false,"sceneViewState":{"m_AlwaysRefresh":false,"showFog":true,"showSkybox":true,"showFlares":true,"showImageEffects":true,"showParticleSystems":true,"showVisualEffectGraphs":true,"m_FxEnabled":true},"in2DMode":false,"pivot":{"x":-33.145301818847659,"y":1.4982939958572388,"z":7.187110900878906},"rotation":{"x":-0.12635283172130586,"y":-0.8472890257835388,"z":0.23259253799915315,"w":-0.4607444107532501},"size":0.702109694480896,"orthographic":false}